Workbook
Name Amount: Data!$D:$D
Name Category: Data!$B:$B
Name Date: Data!$A:$A
Name Description: Data!$C:$C
Name Payment_Method: Data!$E:$E

Sheet Data
A1: Date | B1: Transport | C1: Description | D1: Amount | E1: Payment Method | G1: Category | H1: Monthly Budget | I1: Total Spent | J1: Remaining | K1: Status
A2: 45672 | B2: Food | C2: Grocery shopping | D2: 85.5 | E2: Card | G2: Food | H2: 400 | I2: =SUMIF($B:$B,"Food",$D:$D) -> 307.5 | J2: =H2-I2 -> 92.5 | K2: =IF(J2<0,"Over Budget","OK") -> OK
A3: 45673 | B3: Transport | C3: Gas station | D3: 45 | E3: Cash | G3: Transport | H3: 200 | I3: =SUMIF($B:$B,"Transport",$D:$D) -> 185 | J3: =H3-I3 -> 15 | K3: =IF(J3<0,"Over Budget","OK") -> OK
A4: 45673 | B4: Entertainment | C4: Movie Tickets | D4: 30 | E4: Card | G4: Utilities | H4: 150 | I4: =SUMIF($B:$B,"Utilities",$D:$D) -> 227 | J4: =H4-I4 -> -77 | K4: =IF(J4<0,"Over Budget","OK") -> Over Budget
A5: 45674 | B5: Food | C5: Restaurant lunch | D5: 22.5 | E5: Card | G5: Entertainment | H5: 100 | I5: =SUMIF($B:$B,"Entertainment",$D:$D) -> 149.98 | J5: =H5-I5 -> -49.98 | K5: =IF(J5<0,"Over Budget","OK") -> Over Budget
A6: 45675 | B6: Utilities | C6: Electric Bill | D6: 120 | E6: Bank Transfer | G6: Shopping | H6: 300 | I6: =SUMIF($B:$B,"Shopping",$D:$D) -> 331 | J6: =H6-I6 -> -31 | K6: =IF(J6<0,"Over Budget","OK") -> Over Budget
A7: 45703 | B7: Shopping | C7: New shoes | D7: 89 | E7: Card | G7: Other | H7: 100 | I7: =SUMIF($B:$B,"Other",$D:$D) -> 69 | J7: =H7-I7 -> 31 | K7: =IF(J7<0,"Over Budget","OK") -> OK
A8: 45704 | B8: Food | C8: Coffee shop | D8: 15.5 | E8: Cash
A9: 45704 | B9: Transport | C9: Uber ride | D9: 22 | E9: Card
A10: 45705 | B10: Other | C10: Pharmacy | D10: 34 | E10: Card
A11: 45706 | B11: Food | C11: Lunch takeout | D11: 18.5 | E11: Card
A12: 45731 | B12: Entertainment | C12: Concert Tickets | D12: 95 | E12: Card
A13: 45732 | B13: Utilities | C13: Internet bill | D13: 65 | E13: Bank Transfer
A14: 45732 | B14: Food | C14: Breakfast café | D14: 12 | E14: Cash
A15: 45733 | B15: Transport | C15: Gas station | D15: 48 | E15: Card
A16: 45734 | B16: Shopping | C16: Electronics | D16: 175 | E16: Card
A17: 45762 | B17: Food | C17: Grocery shopping | D17: 98 | E17: Card
A18: 45763 | B18: Transport | C18: Parking fee | D18: 15 | E18: Cash
A19: 45763 | B19: Entertainment | C19: Streaming subscription | D19: 14.99 | E19: Card
... A26: 45855 | B26: Entertainment | C26: Gaming subscription | D26: 9.99 | E26: Card

Sheet Dashboard
A1: Expense Tracker Dashboard
A2: 2025 Summary
A4: Total Budget | C4: Total Spent | E4: Remaining | G4: % Budget Used
A5: =SUM(Data!H:H) -> 1250 | C5: =SUM(Data!I:I) -> 1269.48 | E5: =SUM(Data!J:J) -> -19.48 | G5: =C5/A5 -> 1.015584
A7: Total Transactions | C7: Average Transactions | E7: Over Budget Categories | G7: Largest Single Expense
A8: =COUNTA(Data!A:A)-1 -> 25 | C8: =C5/A8 -> 50.7792 | E8: =COUNTIF(Data!K:K,"Over Budget") -> 3 | G8: =MAX(Data!D:D) -> 175
A10: Budget Breakdown By Category
A11: Category | B11: Budget | C11: Spent | D11: Remaining | E11: % Used | F11: Status
A12: Food | B12: =Data!H2 -> 400 | C12: =Data!I2 -> 307.5 | D12: =Data!J2 -> 92.5 | E12: =C12/B12 -> 0.76875 | F12: =Data!K2 -> OK
A13: Transport | B13: =Data!H3 -> 200 | C13: =Data!I3 -> 185 | D13: =Data!J3 -> 15 | E13: =C13/B13 -> 0.925 | F13: =Data!K3 -> OK
A14: Utilities | B14: =Data!H4 -> 150 | C14: =Data!I4 -> 227 | D14: =Data!J4 -> -77 | E14: =C14/B14 -> 1.5133333 | F14: =Data!K4 -> Over Budget
A15: Entertainment | B15: =Data!H5 -> 100 | C15: =Data!I5 -> 149.98 | D15: =Data!J5 -> -49.98 | E15: =C15/B15 -> 1.4998 | F15: =Data!K5 -> Over Budget
A16: Shopping | B16: =Data!H6 -> 300 | C16: =Data!I6 -> 331 | D16: =Data!J6 -> -31 | E16: =C16/B16 -> 1.1033333 | F16: =Data!K6 -> Over Budget
A17: Other | B17: =Data!H7 -> 100 | C17: =Data!I7 -> 69 | D17: =Data!J7 -> 31 | E17: =C17/B17 -> 0.69 | F17: =Data!K7 -> OK
A19: Visual Breakdown
A37: Key Insights
A38: * You are currently over the budget by: | B38: =ABS(E5) -> 19.48
A39: * Your top spending category is: | B39: =INDEX(A12:A17, MATCH(MAX(C12:C17),C12:C17,0)) -> Shopping
A40: * You have spent in: | B40: =COUNTA(Data!B:B)-1 -> 25 | C40: Transactions this month
A41: You are spending on average: | B41: =C8 -> 50.7792 | C41: per transaction
